Workbook

Sheet 說明
B2: 賽馬模擬遊戲 — 數值平衡試算表
B5: 用途
B6: 把 docs/ 裡已經定案的公式（比賽公式、體力系統、培育系統訓練公式、財務系統）搬進試算表，
B7: 用實際數字跑一遍，檢查數值感覺是否合理，而不是只停留在紙上規則。
B9: 包含分頁
B10: 1. 對照表 — 各項倍率/等級換算表，來源皆為 docs 內已定案的數值。
B11: 2. 屬性設定 — 8 匹測試馬的屬性、跑法、戰術、騎師能力輸入區，已預填 8 種不同類型的範例馬。
B12: 3. 比賽模擬 — 依「階段式排名模擬」規則，逐階段計算 8 匹馬的表現與最終名次。
B13: 4. 訓練成長模擬 — 單一屬性連續多週訓練後的成長曲線，檢查多久能練到潛力上限附近。
B14: 5. 財務模擬 — 一個小馬房(5匹馬)一整年的現金流試算，檢查收支是否撐得住。
B15: 6. 財務系統進階 — 在財務模擬的基礎上加入拍賣購馬、分級獎金期望值、人員分成，檢查一次性大額
B16: 支出/收入疊加常態現金流時，是否會把資金打到負值。
... B52: 實際數值仍需要你依測試結果調整。

Sheet 對照表
A1: 狀態 | B1: 倍率 | D1: 適性等級 | E1: 倍率(假設)
A2: S | B2: 1.2 | D2: S | E2: 1.15
A3: A | B3: 1.1 | D3: A | E3: 1.05
A4: B | B4: 1 | D4: B | E4: 1
A5: C | B5: 0.9 | D5: C | E5: 0.95
A6: D | B6: 0.8 | D6: D | E6: 0.85
D8: 來源: 馬匹系統.md 只給了「明顯/小幅加成/標準/小幅懲罰/明顯懲罰」的文字描述，倍率為本表假設值。
A9: 跑法 | B9: 起跑 | C9: 前段 | D9: 中段 | E9: 後段 | F9: 彎道 | G9: 衝刺
A10: 逃 | B10: 1.1 | C10: 1.15 | D10: 1 | E10: 0.9 | F10: 1 | G10: 0.85
A11: 先 | B11: 0.9 | C11: 1.05 | D11: 1.1 | E11: 1 | F11: 1 | G11: 0.9
A12: 差 | B12: 0.9 | C12: 1 | D12: 1.1 | E12: 1.05 | F12: 1 | G12: 0.9
A13: 追 | B13: 0.85 | C13: 0.9 | D13: 1 | E13: 1.1 | F13: 1 | G13: 1.15
A15: 來源: 馬匹/馬匹系統.md「跑法適配度」，數值逐字照抄；彎道欄為訂正後新增，固定1.00(跑法不影響過彎)。
A16: 跑法 | B16: 起跑 | C16: 前段 | D16: 中段 | E16: 後段 | F16: 衝刺
A17: 逃 | B17: 1.15 | C17: 1.2 | D17: 1 | E17: 0.9 | F17: 0.85
A18: 先 | B18: 1 | C18: 1.05 | D18: 1.05 | E18: 1 | F18: 0.95
A19: 差 | B19: 0.95 | C19: 0.95 | D19: 1 | E19: 1.05 | F19: 1.05
A20: 追 | B20: 0.9 | C20: 0.9 | D20: 0.95 | E20: 1.05 | F20: 1.15
A22: 來源: 比賽/體力系統.md「跑法修正」，數值逐字照抄。
A24: 階段 | B24: 基準剩餘體力% | C24: 基礎消耗(與前一階段差)
A25: 起跑 | B25: 100 | C25: -
A26: 前段 | B26: 88 | C26: 12
A27: 中段 | B27: 64 | C27: 24
A28: 後段 | B28: 37 | C28: 27
A29: 衝刺 | B29: 12 | C29: 25
A31: 來源: 比賽/體力系統.md「基準體力曲線」。基礎消耗＝相鄰兩階段剩餘體力%的差值，供比賽模擬分頁的體力試算使用。

Sheet 屬性設定
A1: 馬匹名稱 | B1: 速度 | C1: 耐力 | D1: 加速 | E1: 力量 | F1: 根性 | G1: 智力 | H1: 起跑 | I1: 彎道 | J1: 戰術(屬性) | K1: 精神 | L1: 健康 | M1: 跑法 | N1: 距離適性等級 | O1: 場地適性等級 | P1: 狀態等級 | Q1: 負磅差(kg) | R1: 騎師修正(整體) | S1: 騎師-位置判斷 | T1: 騎師-節奏控制 | U1: 騎師-路線選擇 | V1: 特性加成% | W1: 戰術波動% | X1: 隨機波動% | Y1: 戰術體力修正
A2: 全能強馬 | B2: 82 | C2: 78 | D2: 80 | E2: 75 | F2: 78 | G2: 72 | H2: 76 | I2: 74 | J2: 70 | K2: 75 | L2: 80 | M2: 逃 | N2: A | O2: A | P2: S | Q2: 0 | R2: 1.05 | S2: 85 | T2: 82 | U2: 78 | V2: 0.06 | W2: 0.08 | X2: 0.02 | Y2: 1
A3: 速度型快馬 | B3: 90 | C3: 55 | D3: 85 | E3: 60 | F3: 50 | G3: 60 | H3: 82 | I3: 55 | J3: 60 | K3: 55 | L3: 70 | M3: 逃 | N3: B | O3: B | P3: A | Q3: -1 | R3: 0.95 | S3: 70 | T3: 68 | U3: 60 | V3: 0.05 | W3: 0.05 | X3: -0.03 | Y3: 1.05
A4: 耐力追込馬 | B4: 60 | C4: 88 | D4: 55 | E4: 65 | F4: 82 | G4: 65 | H4: 55 | I4: 60 | J4: 65 | K4: 70 | L4: 75 | M4: 追 | N4: A | O4: B | P4: B | Q4: 2 | R4: 1 | S4: 75 | T4: 78 | U4: 80 | V4: 0.04 | W4: 0.1 | X4: 0.01 | Y4: 0.95
A5: 平衡中庸馬 | B5: 65 | C5: 65 | D5: 65 | E5: 65 | F5: 65 | G5: 65 | H5: 65 | I5: 65 | J5: 65 | K5: 65 | L5: 65 | M5: 先 | N5: B | O5: B | P5: B | Q5: 1 | R5: 1 | S5: 65 | T5: 65 | U5: 65 | V5: 0 | W5: 0 | X5: 0 | Y5: 1
A6: 潛力新星 | B6: 45 | C6: 42 | D6: 48 | E6: 40 | F6: 44 | G6: 50 | H6: 42 | I6: 40 | J6: 45 | K6: 46 | L6: 55 | M6: 差 | N6: C | O6: C | P6: B | Q6: 0 | R6: 0.9 | S6: 55 | T6: 55 | U6: 55 | V6: 0.03 | W6: 0.02 | X6: -0.02 | Y6: 1
A7: 老將經驗馬 | B7: 68 | C7: 70 | D7: 62 | E7: 68 | F7: 72 | G7: 88 | H7: 70 | I7: 68 | J7: 66 | K7: 90 | L7: 68 | M7: 先 | N7: A | O7: B | P7: B | Q7: 0 | R7: 1.1 | S7: 88 | T7: 85 | U7: 88 | V7: 0.02 | W7: 0.03 | X7: 0 | Y7: 0.9
A8: 彎道巧手馬 | B8: 66 | C8: 62 | D8: 64 | E8: 85 | F8: 60 | G8: 68 | H8: 62 | I8: 92 | J8: 68 | K8: 62 | L8: 72 | M8: 先 | N8: B | O8: S | P8: B | Q8: -2 | R8: 1 | S8: 72 | T8: 70 | U8: 66 | V8: 0.07 | W8: 0.04 | X8: 0.01 | Y8: 1
A9: 衝刺爆發馬 | B9: 78 | C9: 60 | D9: 82 | E9: 58 | F9: 84 | G9: 58 | H9: 60 | I9: 58 | J9: 62 | K9: 55 | L9: 78 | M9: 追 | N9: B | O9: B | P9: A | Q9: 1 | R9: 0.95 | S9: 68 | T9: 66 | U9: 62 | V9: 0.05 | W9: 0.09 | X9: 0.02 | Y9: 1.1
A11: 上面 8 匹是範例測試馬(涵蓋強/弱、四種跑法、不同適性)，全部欄位皆可自行修改。
A12: 騎師-位置判斷/節奏控制/路線選擇：對應 比賽/騎師AI.md 的騎師能力，供「騎師適配度」公式使用，採 0~100 尺度。

Sheet 比賽模擬
A1: 距離修正(0.8~1.3) | B1: 1 | D1: 這兩格模擬「這場賽事」的距離/場地體力消耗修正(來自 體力系統.md)，套用在全部 8 匹馬身上。
A2: 場地修正(1.0~1.2) | B2: 1
A4: 馬匹名稱 | B4: 起跑_基礎 | C4: 起跑_修正後 | D4: 起跑_全場平均 | E4: 起跑_相對 | F4: 起跑_位置值 | G4: 前段_基礎 | H4: 前段_修正後 | I4: 前段_全場平均 | J4: 前段_相對 | K4: 前段_位置值 | L4: 中段_基礎 | M4: 中段_修正後 | N4: 中段_全場平均 | O4: 中段_相對 | P4: 中段_位置值 | Q4: 後段_基礎 | R4: 後段_修正後 | S4: 後段_全場平均 | T4: 後段_相對 | U4: 後段_位置值 | V4: 彎道_基礎 | W4: 彎道_修正後 | X4: 彎道_全場平均 | Y4: 彎道_相對 | Z4: 彎道_位置值 | AA4: 衝刺_基礎 | AB4: 衝刺_修正後 | AC4: 衝刺_全場平均 | AD4: 衝刺_相對 | AE4: 衝刺_位置值(終點) | AF4: 最終名次 | AG4: 外部乘數(輔助) | AH4: 耐力修正(輔助) | AI4: 前段消耗 | AJ4: 前段剩餘 | AK4: 中段消耗 | AL4: 中段剩餘 | AM4: 後段消耗 | AN4: 後段剩餘
A5: =屬性設定!A2 -> 全能強馬 | B5: =屬性設定!D2*0.3+屬性設定!H2*0.5+屬性設定!K2*0.2 -> 77 | C5: =B5*$AG5*INDEX(對照表!$B$10:$B$13,MATCH(屬性設定!M2,對照表!$A$10:$A$13,0)) -> 137.39228 | D5: =AVERAGE(C$5:C$12) -> 75.44104 | E5: =(C5-D5)/D5 -> 0.82118757 | F5: =AVERAGE(E5) -> 0.82118757 | G5: =屬性設定!B2*0.65+(屬性設定!S2*0.6+屬性設定!T2*0.4)*0.35 -> 82.63 | H5: =G5*$AG5*INDEX(對照表!$C$10:$C$13,MATCH(屬性設定!M2,對照表!$A$10:$A$13,0)) -> 154.13971 | I5: =AVERAGE(H$5:H$12) -> 88.686238 | J5: =(H5-I5)/I5 -> 0.73803412 | K5: =AVERAGE(E5,J5) -> 0.77961084 | L5: =屬性設定!B2*0.3+屬性設定!C2*0.3+(屬性設定!T2*0.5+屬性設定!U2*0.5)*0.4 -> 80 | M5: =L5*$AG5*INDEX(對照表!$D$10:$D$13,MATCH(屬性設定!M2,對照表!$A$10:$A$13,0)) -> 129.76839 | N5: =AVERAGE(M$5:M$12) -> 86.33134 | O5: =(M5-N5)/N5 -> 0.5031435 | P5: =AVERAGE(E5,J5,O5) -> 0.68745506 | Q5: =屬性設定!C2*0.5+屬性設定!F2*0.2+AN5*0.3 -> 67.89672 | R5: =Q5*$AG5*INDEX(對照表!$E$10:$E$13,MATCH(屬性設定!M2,對照表!$A$10:$A$13,0)) -> 99.122042 | S5: =AVERAGE(R$5:R$12) -> 70.390503 | T5: =(R5-S5)/S5 -> 0.40817351 | U5: =AVERAGE(E5,J5,O5,T5) -> 0.61763467 | V5: =屬性設定!E2*0.2+屬性設定!G2*0.4+屬性設定!I2*0.4 -> 73.4 | W5: =V5*$AG5*INDEX(對照表!$F$10:$F$13,MATCH(屬性設定!M2,對照表!$A$10:$A$13,0)) -> 119.0625 | X5: =AVERAGE(W$5:W$12) -> 78.704509 | Y5: =(W5-X5)/X5 -> 0.51277863 | Z5: =AVERAGE(E5,J5,O5,T5,Y5) -> 0.59666346 | AA5: =屬性設定!B2*0.4+屬性設定!D2*0.4+屬性設定!F2*0.2 -> 80.4 | AB5: =AA5*$AG5*INDEX(對照表!$G$10:$G$13,MATCH(屬性設定!M2,對照表!$A$10:$A$13,0)) -> 110.85465 | AC5: =AVERAGE(AB$5:AB$12) -> 78.267362 | AD5: =(AB5-AC5)/AC5 -> 0.41635856 | AE5: =AVERAGE(E5,J5,O5,T5,Y5,AD5) -> 0.56661265 | AF5: =RANK(AE5,AE$5:AE$12,0) -> 1 | AG5: =屬性設定!R2*INDEX(對照表!$E$2:$E$6,MATCH(屬性設定!N2,對照表!$D$2:$D$6,0))*INDEX(對照表!$E$2:$E$6,MATCH(屬性設定!O2,對照表!$D$2:$D$6,0))*INDEX(對照表!$B$2:$B$6,MATCH(屬性設定!P2,對照表!$A$2:$A$6,0))*(1-0.01*屬性設定!Q2)*(1+屬性設定!V2)*(1+屬性設定!W2)*(1+屬性設定!X2) -> 1.6221049 | AH5: =1.2-(屬性設定!C2/100)*0.4 -> 0.888 | AI5: =12*$B$1*$AH5*INDEX(對照表!$C$17:$C$20,MATCH(屬性設定!M2,對照表!$A$17:$A$20,0))*屬性設定!Y2*$B$2 -> 12.7872 | AJ5: =100-AI5 -> 87.2128 | AK5: =24*$B$1*$AH5*INDEX(對照表!$D$17:$D$20,MATCH(屬性設定!M2,對照表!$A$17:$A$20,0))*屬性設定!Y2*$B$2 -> 21.312 | AL5: =AJ5-AK5 -> 65.9008 | AM5: =27*$B$1*$AH5*INDEX(對照表!$E$17:$E$20,MATCH(屬性設定!M2,對照表!$A$17:$A$20,0))*屬性設定!Y2*$B$2 -> 21.5784 | AN5: =AL5-AM5 -> 44.3224
A6: =屬性設定!A3 -> 速度型快馬 | B6: =屬性設定!D3*0.3+屬性設定!H3*0.5+屬性設定!K3*0.2 -> 77.5 | C6: =B6*$AG6*INDEX(對照表!$B$10:$B$13,MATCH(屬性設定!M3,對照表!$A$10:$A$13,0)) -> 96.223774 | D6: =AVERAGE(C$5:C$12) -> 75.44104 | E6: =(C6-D6)/D6 -> 0.27548312 | F6: =AVERAGE(E6) -> 0.27548312 | G6: =屬性設定!B3*0.65+(屬性設定!S3*0.6+屬性設定!T3*0.4)*0.35 -> 82.72 | H6: =G6*$AG6*INDEX(對照表!$C$10:$C$13,MATCH(屬性設定!M3,對照表!$A$10:$A$13,0)) -> 107.37332 | I6: =AVERAGE(H$5:H$12) -> 88.686238 | J6: =(H6-I6)/I6 -> 0.21071 | K6: =AVERAGE(E6,J6) -> 0.24309656 | L6: =屬性設定!B3*0.3+屬性設定!C3*0.3+(屬性設定!T3*0.5+屬性設定!U3*0.5)*0.4 -> 69.1 | M6: =L6*$AG6*INDEX(對照表!$D$10:$D$13,MATCH(屬性設定!M3,對照表!$A$10:$A$13,0)) -> 77.994871 | N6: =AVERAGE(M$5:M$12) -> 86.33134 | O6: =(M6-N6)/N6 -> -0.096563644 | P6: =AVERAGE(E6,J6,O6) -> 0.12987649 | Q6: =屬性設定!C3*0.5+屬性設定!F3*0.2+AN6*0.3 -> 48.14451 | R6: =Q6*$AG6*INDEX(對照表!$E$10:$E$13,MATCH(屬性設定!M3,對照表!$A$10:$A$13,0)) -> 48.907704 | S6: =AVERAGE(R$5:R$12) -> 70.390503 | T6: =(R6-S6)/S6 -> -0.30519457 | U6: =AVERAGE(E6,J6,O6,T6) -> 0.021108728 | V6: =屬性設定!E3*0.2+屬性設定!G3*0.4+屬性設定!I3*0.4 -> 58 | W6: =V6*$AG6*INDEX(對照表!$F$10:$F$13,MATCH(屬性設定!M3,對照表!$A$10:$A$13,0)) -> 65.466028 | X6: =AVERAGE(W$5:W$12) -> 78.704509 | Y6: =(W6-X6)/X6 -> -0.16820487 | Z6: =AVERAGE(E6,J6,O6,T6,Y6) -> -0.016753991 | AA6: =屬性設定!B3*0.4+屬性設定!D3*0.4+屬性設定!F3*0.2 -> 80 | AB6: =AA6*$AG6*INDEX(對照表!$G$10:$G$13,MATCH(屬性設定!M3,對照表!$A$10:$A$13,0)) -> 76.753274 | AC6: =AVERAGE(AB$5:AB$12) -> 78.267362 | AD6: =(AB6-AC6)/AC6 -> -0.019345082 | AE6: =AVERAGE(E6,J6,O6,T6,Y6,AD6) -> -0.017185839 | AF6: =RANK(AE6,AE$5:AE$12,0) -> 6 | AG6: =屬性設定!R3*INDEX(對照表!$E$2:$E$6,MATCH(屬性設定!N3,對照表!$D$2:$D$6,0))*INDEX(對照表!$E$2:$E$6,MATCH(屬性設定!O3,對照表!$D$2:$D$6,0))*INDEX(對照表!$B$2:$B$6,MATCH(屬性設定!P3,對照表!$A$2:$A$6,0))*(1-0.01*屬性設定!Q3)*(1+屬性設定!V3)*(1+屬性設定!W3)*(1+屬性設定!X3) -> 1.1287246 | AH6: =1.2-(屬性設定!C3/100)*0.4 -> 0.98 | AI6: =12*$B$1*$AH6*INDEX(對照表!$C$17:$C$20,MATCH(屬性設定!M3,對照表!$A$17:$A$20,0))*屬性設定!Y3*$B$2 -> 14.8176 | AJ6: =100-AI6 -> 85.1824 | AK6: =24*$B$1*$AH6*INDEX(對照表!$D$17:$D$20,MATCH(屬性設定!M3,對照表!$A$17:$A$20,0))*屬性設定!Y3*$B$2 -> 24.696 | AL6: =AJ6-AK6 -> 60.4864 | AM6: =27*$B$1*$AH6*INDEX(對照表!$E$17:$E$20,MATCH(屬性設定!M3,對照表!$A$17:$A$20,0))*屬性設定!Y3*$B$2 -> 25.0047 | AN6: =AL6-AM6 -> 35.4817
A7: =屬性設定!A4 -> 耐力追込馬 | B7: =屬性設定!D4*0.3+屬性設定!H4*0.5+屬性設定!K4*0.2 -> 58 | C7: =B7*$AG7*INDEX(對照表!$B$10:$B$13,MATCH(屬性設定!M4,對照表!$A$10:$A$13,0)) -> 58.615125 | D7: =AVERAGE(C$5:C$12) -> 75.44104 | E7: =(C7-D7)/D7 -> -0.22303399 | F7: =AVERAGE(E7) -> -0.22303399 | G7: =屬性設定!B4*0.65+(屬性設定!S4*0.6+屬性設定!T4*0.4)*0.35 -> 65.67 | H7: =G7*$AG7*INDEX(對照表!$C$10:$C$13,MATCH(屬性設定!M4,對照表!$A$10:$A$13,0)) -> 70.270379 | I7: =AVERAGE(H$5:H$12) -> 88.686238 | J7: =(H7-I7)/I7 -> -0.20765182 | K7: =AVERAGE(E7,J7) -> -0.2153429 | L7: =屬性設定!B4*0.3+屬性設定!C4*0.3+(屬性設定!T4*0.5+屬性設定!U4*0.5)*0.4 -> 76 | M7: =L7*$AG7*INDEX(對照表!$D$10:$D$13,MATCH(屬性設定!M4,對照表!$A$10:$A$13,0)) -> 90.36003 | N7: =AVERAGE(M$5:M$12) -> 86.33134 | O7: =(M7-N7)/N7 -> 0.046665441 | P7: =AVERAGE(E7,J7,O7) -> -0.12800679 | Q7: =屬性設定!C4*0.5+屬性設定!F4*0.2+AN7*0.3 -> 75.427924 | R7: =Q7*$AG7*INDEX(對照表!$E$10:$E$13,MATCH(屬性設定!M4,對照表!$A$10:$A$13,0)) -> 98.647847 | S7: =AVERAGE(R$5:R$12) -> 70.390503 | T7: =(R7-S7)/S7 -> 0.40143688 | U7: =AVERAGE(E7,J7,O7,T7) -> 0.00435413 | V7: =屬性設定!E4*0.2+屬性設定!G4*0.4+屬性設定!I4*0.4 -> 63 | W7: =V7*$AG7*INDEX(對照表!$F$10:$F$13,MATCH(屬性設定!M4,對照表!$A$10:$A$13,0)) -> 74.903709 | X7: =AVERAGE(W$5:W$12) -> 78.704509 | Y7: =(W7-X7)/X7 -> -0.048292027 | Z7: =AVERAGE(E7,J7,O7,T7,Y7) -> -0.0061751015 | AA7: =屬性設定!B4*0.4+屬性設定!D4*0.4+屬性設定!F4*0.2 -> 62.4 | AB7: =AA7*$AG7*INDEX(對照表!$G$10:$G$13,MATCH(屬性設定!M4,對照表!$A$10:$A$13,0)) -> 85.318891 | AC7: =AVERAGE(AB$5:AB$12) -> 78.267362 | AD7: =(AB7-AC7)/AC7 -> 0.090095393 | AE7: =AVERAGE(E7,J7,O7,T7,Y7,AD7) -> 0.009869981 | AF7: =RANK(AE7,AE$5:AE$12,0) -> 5 | AG7: =屬性設定!R4*INDEX(對照表!$E$2:$E$6,MATCH(屬性設定!N4,對照表!$D$2:$D$6,0))*INDEX(對照表!$E$2:$E$6,MATCH(屬性設定!O4,對照表!$D$2:$D$6,0))*INDEX(對照表!$B$2:$B$6,MATCH(屬性設定!P4,對照表!$A$2:$A$6,0))*(1-0.01*屬性設定!Q4)*(1+屬性設定!V4)*(1+屬性設定!W4)*(1+屬性設定!X4) -> 1.1889478 | AH7: =1.2-(屬性設定!C4/100)*0.4 -> 0.848 | AI7: =12*$B$1*$AH7*INDEX(對照表!$C$17:$C$20,MATCH(屬性設定!M4,對照表!$A$17:$A$20,0))*屬性設定!Y4*$B$2 -> 8.70048 | AJ7: =100-AI7 -> 91.29952 | AK7: =24*$B$1*$AH7*INDEX(對照表!$D$17:$D$20,MATCH(屬性設定!M4,對照表!$A$17:$A$20,0))*屬性設定!Y4*$B$2 -> 18.36768 | AL7: =AJ7-AK7 -> 72.93184 | AM7: =27*$B$1*$AH7*INDEX(對照表!$E$17:$E$20,MATCH(屬性設定!M4,對照表!$A$17:$A$20,0))*屬性設定!Y4*$B$2 -> 22.83876 | AN7: =AL7-AM7 -> 50.09308
A8: =屬性設定!A5 -> 平衡中庸馬 | B8: =屬性設定!D5*0.3+屬性設定!H5*0.5+屬性設定!K5*0.2 -> 65 | C8: =B8*$AG8*INDEX(對照表!$B$10:$B$13,MATCH(屬性設定!M5,對照表!$A$10:$A$13,0)) -> 57.915 | D8: =AVERAGE(C$5:C$12) -> 75.44104 | E8: =(C8-D8)/D8 -> -0.23231441 | F8: =AVERAGE(E8) -> -0.23231441 | G8: =屬性設定!B5*0.65+(屬性設定!S5*0.6+屬性設定!T5*0.4)*0.35 -> 65 | H8: =G8*$AG8*INDEX(對照表!$C$10:$C$13,MATCH(屬性設定!M5,對照表!$A$10:$A$13,0)) -> 67.5675 | I8: =AVERAGE(H$5:H$12) -> 88.686238 | J8: =(H8-I8)/I8 -> -0.23812869 | K8: =AVERAGE(E8,J8) -> -0.23522155 | L8: =屬性設定!B5*0.3+屬性設定!C5*0.3+(屬性設定!T5*0.5+屬性設定!U5*0.5)*0.4 -> 65 | M8: =L8*$AG8*INDEX(對照表!$D$10:$D$13,MATCH(屬性設定!M5,對照表!$A$10:$A$13,0)) -> 70.785 | N8: =AVERAGE(M$5:M$12) -> 86.33134 | O8: =(M8-N8)/N8 -> -0.18007759 | P8: =AVERAGE(E8,J8,O8) -> -0.21684023 | Q8: =屬性設定!C5*0.5+屬性設定!F5*0.2+AN8*0.3 -> 57.2264 | R8: =Q8*$AG8*INDEX(對照表!$E$10:$E$13,MATCH(屬性設定!M5,對照表!$A$10:$A$13,0)) -> 56.654136 | S8: =AVERAGE(R$5:R$12) -> 70.390503 | T8: =(R8-S8)/S8 -> -0.19514518 | U8: =AVERAGE(E8,J8,O8,T8) -> -0.21141647 | V8: =屬性設定!E5*0.2+屬性設定!G5*0.4+屬性設定!I5*0.4 -> 65 | W8: =V8*$AG8*INDEX(對照表!$F$10:$F$13,MATCH(屬性設定!M5,對照表!$A$10:$A$13,0)) -> 64.35 | X8: =AVERAGE(W$5:W$12) -> 78.704509 | Y8: =(W8-X8)/X8 -> -0.18238484 | Z8: =AVERAGE(E8,J8,O8,T8,Y8) -> -0.20561014 | AA8: =屬性設定!B5*0.4+屬性設定!D5*0.4+屬性設定!F5*0.2 -> 65 | AB8: =AA8*$AG8*INDEX(對照表!$G$10:$G$13,MATCH(屬性設定!M5,對照表!$A$10:$A$13,0)) -> 57.915 | AC8: =AVERAGE(AB$5:AB$12) -> 78.267362 | AD8: =(AB8-AC8)/AC8 -> -0.26003639 | AE8: =AVERAGE(E8,J8,O8,T8,Y8,AD8) -> -0.21468118 | AF8: =RANK(AE8,AE$5:AE$12,0) -> 7 | AG8: =屬性設定!R5*INDEX(對照表!$E$2:$E$6,MATCH(屬性設定!N5,對照表!$D$2:$D$6,0))*INDEX(對照表!$E$2:$E$6,MATCH(屬性設定!O5,對照表!$D$2:$D$6,0))*INDEX(對照表!$B$2:$B$6,MATCH(屬性設定!P5,對照表!$A$2:$A$6,0))*(1-0.01*屬性設定!Q5)*(1+屬性設定!V5)*(1+屬性設定!W5)*(1+屬性設定!X5) -> 0.99 | AH8: =1.2-(屬性設定!C5/100)*0.4 -> 0.94 | AI8: =12*$B$1*$AH8*INDEX(對照表!$C$17:$C$20,MATCH(屬性設定!M5,對照表!$A$17:$A$20,0))*屬性設定!Y5*$B$2 -> 11.844 | AJ8: =100-AI8 -> 88.156 | AK8: =24*$B$1*$AH8*INDEX(對照表!$D$17:$D$20,MATCH(屬性設定!M5,對照表!$A$17:$A$20,0))*屬性設定!Y5*$B$2 -> 23.688 | AL8: =AJ8-AK8 -> 64.468 | AM8: =27*$B$1*$AH8*INDEX(對照表!$E$17:$E$20,MATCH(屬性設定!M5,對照表!$A$17:$A$20,0))*屬性設定!Y5*$B$2 -> 25.38 | AN8: =AL8-AM8 -> 39.088
A9: =屬性設定!A6 -> 潛力新星 | B9: =屬性設定!D6*0.3+屬性設定!H6*0.5+屬性設定!K6*0.2 -> 44.6 | C9: =B9*$AG9*INDEX(對照表!$B$10:$B$13,MATCH(屬性設定!M6,對照表!$A$10:$A$13,0)) -> 33.568394 | D9: =AVERAGE(C$5:C$12) -> 75.44104 | E9: =(C9-D9)/D9 -> -0.55503803 | F9: =AVERAGE(E9) -> -0.55503803 | G9: =屬性設定!B6*0.65+(屬性設定!S6*0.6+屬性設定!T6*0.4)*0.35 -> 48.5 | H9: =G9*$AG9*INDEX(對照表!$C$10:$C$13,MATCH(屬性設定!M6,對照表!$A$10:$A$13,0)) -> 40.559718 | I9: =AVERAGE(H$5:H$12) -> 88.686238 | J9: =(H9-I9)/I9 -> -0.54266051 | K9: =AVERAGE(E9,J9) -> -0.54884927 | L9: =屬性設定!B6*0.3+屬性設定!C6*0.3+(屬性設定!T6*0.5+屬性設定!U6*0.5)*0.4 -> 48.1 | M9: =L9*$AG9*INDEX(對照表!$D$10:$D$13,MATCH(屬性設定!M6,對照表!$A$10:$A$13,0)) -> 44.247726 | N9: =AVERAGE(M$5:M$12) -> 86.33134 | O9: =(M9-N9)/N9 -> -0.48746624 | P9: =AVERAGE(E9,J9,O9) -> -0.52838826 | Q9: =屬性設定!C6*0.5+屬性設定!F6*0.2+AN9*0.3 -> 40.063 | R9: =Q9*$AG9*INDEX(對照表!$E$10:$E$13,MATCH(屬性設定!M6,對照表!$A$10:$A$13,0)) -> 35.1792 | S9: =AVERAGE(R$5:R$12) -> 70.390503 | T9: =(R9-S9)/S9 -> -0.50022804 | U9: =AVERAGE(E9,J9,O9,T9) -> -0.52134821 | V9: =屬性設定!E6*0.2+屬性設定!G6*0.4+屬性設定!I6*0.4 -> 44 | W9: =V9*$AG9*INDEX(對照表!$F$10:$F$13,MATCH(屬性設定!M6,對照表!$A$10:$A$13,0)) -> 36.796446 | X9: =AVERAGE(W$5:W$12) -> 78.704509 | Y9: =(W9-X9)/X9 -> -0.53247348 | Z9: =AVERAGE(E9,J9,O9,T9,Y9) -> -0.52357326 | AA9: =屬性設定!B6*0.4+屬性設定!D6*0.4+屬性設定!F6*0.2 -> 46 | AB9: =AA9*$AG9*INDEX(對照表!$G$10:$G$13,MATCH(屬性設定!M6,對照表!$A$10:$A$13,0)) -> 34.62211 | AC9: =AVERAGE(AB$5:AB$12) -> 78.267362 | AD9: =(AB9-AC9)/AC9 -> -0.55764307 | AE9: =AVERAGE(E9,J9,O9,T9,Y9,AD9) -> -0.52925156 | AF9: =RANK(AE9,AE$5:AE$12,0) -> 8 | AG9: =屬性設定!R6*INDEX(對照表!$E$2:$E$6,MATCH(屬性設定!N6,對照表!$D$2:$D$6,0))*INDEX(對照表!$E$2:$E$6,MATCH(屬性設定!O6,對照表!$D$2:$D$6,0))*INDEX(對照表!$B$2:$B$6,MATCH(屬性設定!P6,對照表!$A$2:$A$6,0))*(1-0.01*屬性設定!Q6)*(1+屬性設定!V6)*(1+屬性設定!W6)*(1+屬性設定!X6) -> 0.83628285 | AH9: =1.2-(屬性設定!C6/100)*0.4 -> 1.032 | AI9: =12*$B$1*$AH9*INDEX(對照表!$C$17:$C$20,MATCH(屬性設定!M6,對照表!$A$17:$A$20,0))*屬性設定!Y6*$B$2 -> 11.7648 | AJ9: =100-AI9 -> 88.2352 | AK9: =24*$B$1*$AH9*INDEX(對照表!$D$17:$D$20,MATCH(屬性設定!M6,對照表!$A$17:$A$20,0))*屬性設定!Y6*$B$2 -> 24.768 | AL9: =AJ9-AK9 -> 63.4672 | AM9: =27*$B$1*$AH9*INDEX(對照表!$E$17:$E$20,MATCH(屬性設定!M6,對照表!$A$17:$A$20,0))*屬性設定!Y6*$B$2 -> 29.2572 | AN9: =AL9-AM9 -> 34.21
A10: =屬性設定!A7 -> 老將經驗馬 | B10: =屬性設定!D7*0.3+屬性設定!H7*0.5+屬性設定!K7*0.2 -> 71.6 | C10: =B10*$AG10*INDEX(對照表!$B$10:$B$13,MATCH(屬性設定!M7,對照表!$A$10:$A$13,0)) -> 78.194267 | D10: =AVERAGE(C$5:C$12) -> 75.44104 | E10: =(C10-D10)/D10 -> 0.036495075 | F10: =AVERAGE(E10) -> 0.036495075 | G10: =屬性設定!B7*0.65+(屬性設定!S7*0.6+屬性設定!T7*0.4)*0.35 -> 74.58 | H10: =G10*$AG10*INDEX(對照表!$C$10:$C$13,MATCH(屬性設定!M7,對照表!$A$10:$A$13,0)) -> 95.023508 | I10: =AVERAGE(H$5:H$12) -> 88.686238 | J10: =(H10-I10)/I10 -> 0.071457199 | K10: =AVERAGE(E10,J10) -> 0.053976137 | L10: =屬性設定!B7*0.3+屬性設定!C7*0.3+(屬性設定!T7*0.5+屬性設定!U7*0.5)*0.4 -> 76 | M10: =L10*$AG10*INDEX(對照表!$D$10:$D$13,MATCH(屬性設定!M7,對照表!$A$10:$A$13,0)) -> 101.44383 | N10: =AVERAGE(M$5:M$12) -> 86.33134 | O10: =(M10-N10)/N10 -> 0.17505225 | P10: =AVERAGE(E10,J10,O10) -> 0.094334841 | Q10: =屬性設定!C7*0.5+屬性設定!F7*0.2+AN10*0.3 -> 63.30368 | R10: =Q10*$AG10*INDEX(對照表!$E$10:$E$13,MATCH(屬性設定!M7,對照表!$A$10:$A$13,0)) -> 76.815407 | S10: =AVERAGE(R$5:R$12) -> 70.390503 | T10: =(R10-S10)/S10 -> 0.091275153 | U10: =AVERAGE(E10,J10,O10,T10) -> 0.093569919 | V10: =屬性設定!E7*0.2+屬性設定!G7*0.4+屬性設定!I7*0.4 -> 76 | W10: =V10*$AG10*INDEX(對照表!$F$10:$F$13,MATCH(屬性設定!M7,對照表!$A$10:$A$13,0)) -> 92.221668 | X10: =AVERAGE(W$5:W$12) -> 78.704509 | Y10: =(W10-X10)/X10 -> 0.17174567 | Z10: =AVERAGE(E10,J10,O10,T10,Y10) -> 0.10920507 | AA10: =屬性設定!B7*0.4+屬性設定!D7*0.4+屬性設定!F7*0.2 -> 66.4 | AB10: =AA10*$AG10*INDEX(對照表!$G$10:$G$13,MATCH(屬性設定!M7,對照表!$A$10:$A$13,0)) -> 72.515354 | AC10: =AVERAGE(AB$5:AB$12) -> 78.267362 | AD10: =(AB10-AC10)/AC10 -> -0.073491793 | AE10: =AVERAGE(E10,J10,O10,T10,Y10,AD10) -> 0.078755592 | AF10: =RANK(AE10,AE$5:AE$12,0) -> 3 | AG10: =屬性設定!R7*INDEX(對照表!$E$2:$E$6,MATCH(屬性設定!N7,對照表!$D$2:$D$6,0))*INDEX(對照表!$E$2:$E$6,MATCH(屬性設定!O7,對照表!$D$2:$D$6,0))*INDEX(對照表!$B$2:$B$6,MATCH(屬性設定!P7,對照表!$A$2:$A$6,0))*(1-0.01*屬性設定!Q7)*(1+屬性設定!V7)*(1+屬性設定!W7)*(1+屬性設定!X7) -> 1.213443 | AH10: =1.2-(屬性設定!C7/100)*0.4 -> 0.92 | AI10: =12*$B$1*$AH10*INDEX(對照表!$C$17:$C$20,MATCH(屬性設定!M7,對照表!$A$17:$A$20,0))*屬性設定!Y7*$B$2 -> 10.4328 | AJ10: =100-AI10 -> 89.5672 | AK10: =24*$B$1*$AH10*INDEX(對照表!$D$17:$D$20,MATCH(屬性設定!M7,對照表!$A$17:$A$20,0))*屬性設定!Y7*$B$2 -> 20.8656 | AL10: =AJ10-AK10 -> 68.7016 | AM10: =27*$B$1*$AH10*INDEX(對照表!$E$17:$E$20,MATCH(屬性設定!M7,對照表!$A$17:$A$20,0))*屬性設定!Y7*$B$2 -> 22.356 | AN10: =AL10-AM10 -> 46.3456
A11: =屬性設定!A8 -> 彎道巧手馬 | B11: =屬性設定!D8*0.3+屬性設定!H8*0.5+屬性設定!K8*0.2 -> 62.6 | C11: =B11*$AG11*INDEX(對照表!$B$10:$B$13,MATCH(屬性設定!M8,對照表!$A$10:$A$13,0)) -> 74.276827 | D11: =AVERAGE(C$5:C$12) -> 75.44104 | E11: =(C11-D11)/D11 -> -0.015432091 | F11: =AVERAGE(E11) -> -0.015432091 | G11: =屬性設定!B8*0.65+(屬性設定!S8*0.6+屬性設定!T8*0.4)*0.35 -> 67.82 | H11: =G11*$AG11*INDEX(對照表!$C$10:$C$13,MATCH(屬性設定!M8,對照表!$A$10:$A$13,0)) -> 93.882271 | I11: =AVERAGE(H$5:H$12) -> 88.686238 | J11: =(H11-I11)/I11 -> 0.058588949 | K11: =AVERAGE(E11,J11) -> 0.021578429 | L11: =屬性設定!B8*0.3+屬性設定!C8*0.3+(屬性設定!T8*0.5+屬性設定!U8*0.5)*0.4 -> 65.6 | M11: =L11*$AG11*INDEX(對照表!$D$10:$D$13,MATCH(屬性設定!M8,對照表!$A$10:$A$13,0)) -> 95.133402 | N11: =AVERAGE(M$5:M$12) -> 86.33134 | O11: =(M11-N11)/N11 -> 0.10195674 | P11: =AVERAGE(E11,J11,O11) -> 0.0483712 | Q11: =屬性設定!C8*0.5+屬性設定!F8*0.2+AN11*0.3 -> 54.49312 | R11: =Q11*$AG11*INDEX(對照表!$E$10:$E$13,MATCH(屬性設定!M8,對照表!$A$10:$A$13,0)) -> 71.841961 | S11: =AVERAGE(R$5:R$12) -> 70.390503 | T11: =(R11-S11)/S11 -> 0.020620074 | U11: =AVERAGE(E11,J11,O11,T11) -> 0.041433419 | V11: =屬性設定!E8*0.2+屬性設定!G8*0.4+屬性設定!I8*0.4 -> 81 | W11: =V11*$AG11*INDEX(對照表!$F$10:$F$13,MATCH(屬性設定!M8,對照表!$A$10:$A$13,0)) -> 106.78777 | X11: =AVERAGE(W$5:W$12) -> 78.704509 | Y11: =(W11-X11)/X11 -> 0.35681897 | Z11: =AVERAGE(E11,J11,O11,T11,Y11) -> 0.10451053 | AA11: =屬性設定!B8*0.4+屬性設定!D8*0.4+屬性設定!F8*0.2 -> 64 | AB11: =AA11*$AG11*INDEX(對照表!$G$10:$G$13,MATCH(屬性設定!M8,對照表!$A$10:$A$13,0)) -> 75.937971 | AC11: =AVERAGE(AB$5:AB$12) -> 78.267362 | AD11: =(AB11-AC11)/AC11 -> -0.029761983 | AE11: =AVERAGE(E11,J11,O11,T11,Y11,AD11) -> 0.082131777 | AF11: =RANK(AE11,AE$5:AE$12,0) -> 2 | AG11: =屬性設定!R8*INDEX(對照表!$E$2:$E$6,MATCH(屬性設定!N8,對照表!$D$2:$D$6,0))*INDEX(對照表!$E$2:$E$6,MATCH(屬性設定!O8,對照表!$D$2:$D$6,0))*INDEX(對照表!$B$2:$B$6,MATCH(屬性設定!P8,對照表!$A$2:$A$6,0))*(1-0.01*屬性設定!Q8)*(1+屬性設定!V8)*(1+屬性設定!W8)*(1+屬性設定!X8) -> 1.3183675 | AH11: =1.2-(屬性設定!C8/100)*0.4 -> 0.952 | AI11: =12*$B$1*$AH11*INDEX(對照表!$C$17:$C$20,MATCH(屬性設定!M8,對照表!$A$17:$A$20,0))*屬性設定!Y8*$B$2 -> 11.9952 | AJ11: =100-AI11 -> 88.0048 | AK11: =24*$B$1*$AH11*INDEX(對照表!$D$17:$D$20,MATCH(屬性設定!M8,對照表!$A$17:$A$20,0))*屬性設定!Y8*$B$2 -> 23.9904 | AL11: =AJ11-AK11 -> 64.0144 | AM11: =27*$B$1*$AH11*INDEX(對照表!$E$17:$E$20,MATCH(屬性設定!M8,對照表!$A$17:$A$20,0))*屬性設定!Y8*$B$2 -> 25.704 | AN11: =AL11-AM11 -> 38.3104
A12: =屬性設定!A9 -> 衝刺爆發馬 | B12: =屬性設定!D9*0.3+屬性設定!H9*0.5+屬性設定!K9*0.2 -> 65.6 | C12: =B12*$AG12*INDEX(對照表!$B$10:$B$13,MATCH(屬性設定!M9,對照表!$A$10:$A$13,0)) -> 67.342653 | D12: =AVERAGE(C$5:C$12) -> 75.44104 | E12: =(C12-D12)/D12 -> -0.10734725 | F12: =AVERAGE(E12) -> -0.10734725 | G12: =屬性設定!B9*0.65+(屬性設定!S9*0.6+屬性設定!T9*0.4)*0.35 -> 74.22 | H12: =G12*$AG12*INDEX(對照表!$C$10:$C$13,MATCH(屬性設定!M9,對照表!$A$10:$A$13,0)) -> 80.673503 | I12: =AVERAGE(H$5:H$12) -> 88.686238 | J12: =(H12-I12)/I12 -> -0.09034925 | K12: =AVERAGE(E12,J12) -> -0.098848248 | L12: =屬性設定!B9*0.3+屬性設定!C9*0.3+(屬性設定!T9*0.5+屬性設定!U9*0.5)*0.4 -> 67 | M12: =L12*$AG12*INDEX(對照表!$D$10:$D$13,MATCH(屬性設定!M9,對照表!$A$10:$A$13,0)) -> 80.917463 | N12: =AVERAGE(M$5:M$12) -> 86.33134 | O12: =(M12-N12)/N12 -> -0.062710448 | P12: =AVERAGE(E12,J12,O12) -> -0.086802315 | Q12: =屬性設定!C9*0.5+屬性設定!F9*0.2+AN12*0.3 -> 57.17424 | R12: =Q12*$AG12*INDEX(對照表!$E$10:$E$13,MATCH(屬性設定!M9,對照表!$A$10:$A$13,0)) -> 75.95573 | S12: =AVERAGE(R$5:R$12) -> 70.390503 | T12: =(R12-S12)/S12 -> 0.079062173 | U12: =AVERAGE(E12,J12,O12,T12) -> -0.045336193 | V12: =屬性設定!E9*0.2+屬性設定!G9*0.4+屬性設定!I9*0.4 -> 58 | W12: =V12*$AG12*INDEX(對照表!$F$10:$F$13,MATCH(屬性設定!M9,對照表!$A$10:$A$13,0)) -> 70.047953 | X12: =AVERAGE(W$5:W$12) -> 78.704509 | Y12: =(W12-X12)/X12 -> -0.10998806 | Z12: =AVERAGE(E12,J12,O12,T12,Y12) -> -0.058266566 | AA12: =屬性設定!B9*0.4+屬性設定!D9*0.4+屬性設定!F9*0.2 -> 80.8 | AB12: =AA12*$AG12*INDEX(對照表!$G$10:$G$13,MATCH(屬性設定!M9,對照表!$A$10:$A$13,0)) -> 112.22165 | AC12: =AVERAGE(AB$5:AB$12) -> 78.267362 | AD12: =(AB12-AC12)/AC12 -> 0.43382437 | AE12: =AVERAGE(E12,J12,O12,T12,Y12,AD12) -> 0.023748589 | AF12: =RANK(AE12,AE$5:AE$12,0) -> 4 | AG12: =屬性設定!R9*INDEX(對照表!$E$2:$E$6,MATCH(屬性設定!N9,對照表!$D$2:$D$6,0))*INDEX(對照表!$E$2:$E$6,MATCH(屬性設定!O9,對照表!$D$2:$D$6,0))*INDEX(對照表!$B$2:$B$6,MATCH(屬性設定!P9,對照表!$A$2:$A$6,0))*(1-0.01*屬性設定!Q9)*(1+屬性設定!V9)*(1+屬性設定!W9)*(1+屬性設定!X9) -> 1.2077233 | AH12: =1.2-(屬性設定!C9/100)*0.4 -> 0.96 | AI12: =12*$B$1*$AH12*INDEX(對照表!$C$17:$C$20,MATCH(屬性設定!M9,對照表!$A$17:$A$20,0))*屬性設定!Y9*$B$2 -> 11.4048 | AJ12: =100-AI12 -> 88.5952 | AK12: =24*$B$1*$AH12*INDEX(對照表!$D$17:$D$20,MATCH(屬性設定!M9,對照表!$A$17:$A$20,0))*屬性設定!Y9*$B$2 -> 24.0768 | AL12: =AJ12-AK12 -> 64.5184 | AM12: =27*$B$1*$AH12*INDEX(對照表!$E$17:$E$20,MATCH(屬性設定!M9,對照表!$A$17:$A$20,0))*屬性設定!Y9*$B$2 -> 29.9376 | AN12: =AL12-AM12 -> 34.5808
A14: 說明：位置值＝目前為止各階段「相對表現」的平均值(不再複利連乘)，六階段權重相同。
A15: 最後用「衝刺_位置值(終點)」RANK 出名次，數字越大名次越前面；這是「強者恆強」問題的對策(b)版本。

Sheet 訓練成長模擬
A1: 單一屬性的多週訓練模擬 | D1: 公式來源(訂正版): 培育/培育系統.md「訓練能力」：基礎訓練值 × 潛力餘裕 × 年齡成長倍率 × 訓練師 × 設施 × 狀態
A2: 潛力上限(0~100) | B2: 85
A3: 起始能力值(0~100) | B3: 30
A4: 基礎訓練值(每次訓練) | B4: 2
A5: 訓練師倍率 | B5: 1.1
A6: 設施倍率 | B6: 1.1
A7: 狀態倍率 | B7: 1
A8: 上升期結束週次 | B8: 52
A9: 巔峰期結束週次 | B9: 104
A10: 停滯期結束週次 | B10: 130
A11: 上升期年齡倍率(假設) | B11: 1.2
A12: 巔峰期年齡倍率(假設) | B12: 1
A13: 停滯期年齡倍率(假設) | B13: 0.5
A14: 衰退期年齡倍率(假設) | B14: 0.1
A17: 週次 | B17: 年齡階段 | C17: 年齡倍率 | D17: 本週成長量 | E17: 累積能力值(封頂於潛力上限) | F17: 達潛力上限%
A18: 1 | B18: =IF(A18<=$B$8,"上升期",IF(A18<=$B$9,"巔峰期",IF(A18<=$B$10,"停滯期","衰退期"))) -> 上升期 | C18: =IF(B18="上升期",$B$11,IF(B18="巔峰期",$B$12,IF(B18="停滯期",$B$13,$B$14))) -> 1.2 | D18: =$B$4*(($B$2-$B$3)/100)*C18*$B$5*$B$6*$B$7 -> 1.5972 | E18: =MIN($B$3+D18,$B$2) -> 31.5972 | F18: =E18/$B$2 -> 0.37173176
A19: 2 | B19: =IF(A19<=$B$8,"上升期",IF(A19<=$B$9,"巔峰期",IF(A19<=$B$10,"停滯期","衰退期"))) -> 上升期 | C19: =IF(B19="上升期",$B$11,IF(B19="巔峰期",$B$12,IF(B19="停滯期",$B$13,$B$14))) -> 1.2 | D19: =$B$4*(($B$2-E18)/100)*C19*$B$5*$B$6*$B$7 -> 1.5508173 | E19: =MIN(E18+D19,$B$2) -> 33.148017 | F19: =E19/$B$2 -> 0.38997667
A20: 3 | B20: =IF(A20<=$B$8,"上升期",IF(A20<=$B$9,"巔峰期",IF(A20<=$B$10,"停滯期","衰退期"))) -> 上升期 | C20: =IF(B20="上升期",$B$11,IF(B20="巔峰期",$B$12,IF(B20="停滯期",$B$13,$B$14))) -> 1.2 | D20: =$B$4*(($B$2-E19)/100)*C20*$B$5*$B$6*$B$7 -> 1.5057816 | E20: =MIN(E19+D20,$B$2) -> 34.653799 | F20: =E20/$B$2 -> 0.40769175
A21: 4 | B21: =IF(A21<=$B$8,"上升期",IF(A21<=$B$9,"巔峰期",IF(A21<=$B$10,"停滯期","衰退期"))) -> 上升期 | C21: =IF(B21="上升期",$B$11,IF(B21="巔峰期",$B$12,IF(B21="停滯期",$B$13,$B$14))) -> 1.2 | D21: =$B$4*(($B$2-E20)/100)*C21*$B$5*$B$6*$B$7 -> 1.4620537 | E21: =MIN(E20+D21,$B$2) -> 36.115853 | F21: =E21/$B$2 -> 0.42489238
A22: 5 | B22: =IF(A22<=$B$8,"上升期",IF(A22<=$B$9,"巔峰期",IF(A22<=$B$10,"停滯期","衰退期"))) -> 上升期 | C22: =IF(B22="上升期",$B$11,IF(B22="巔峰期",$B$12,IF(B22="停滯期",$B$13,$B$14))) -> 1.2 | D22: =$B$4*(($B$2-E21)/100)*C22*$B$5*$B$6*$B$7 -> 1.4195956 | E22: =MIN(E21+D22,$B$2) -> 37.535448 | F22: =E22/$B$2 -> 0.44159351
A23: 6 | B23: =IF(A23<=$B$8,"上升期",IF(A23<=$B$9,"巔峰期",IF(A23<=$B$10,"停滯期","衰退期"))) -> 上升期 | C23: =IF(B23="上升期",$B$11,IF(B23="巔峰期",$B$12,IF(B23="停滯期",$B$13,$B$14))) -> 1.2 | D23: =$B$4*(($B$2-E22)/100)*C23*$B$5*$B$6*$B$7 -> 1.3783706 | E23: =MIN(E22+D23,$B$2) -> 38.913819 | F23: =E23/$B$2 -> 0.45780963
A24: 7 | B24: =IF(A24<=$B$8,"上升期",IF(A24<=$B$9,"巔峰期",IF(A24<=$B$10,"停滯期","衰退期"))) -> 上升期 | C24: =IF(B24="上升期",$B$11,IF(B24="巔峰期",$B$12,IF(B24="停滯期",$B$13,$B$14))) -> 1.2 | D24: =$B$4*(($B$2-E23)/100)*C24*$B$5*$B$6*$B$7 -> 1.3383427 | E24: =MIN(E23+D24,$B$2) -> 40.252161 | F24: =E24/$B$2 -> 0.47355484
A25: 8 | B25: =IF(A25<=$B$8,"上升期",IF(A25<=$B$9,"巔峰期",IF(A25<=$B$10,"停滯期","衰退期"))) -> 上升期 | C25: =IF(B25="上升期",$B$11,IF(B25="巔峰期",$B$12,IF(B25="停滯期",$B$13,$B$14))) -> 1.2 | D25: =$B$4*(($B$2-E24)/100)*C25*$B$5*$B$6*$B$7 -> 1.2994772 | E25: =MIN(E24+D25,$B$2) -> 41.551639 | F25: =E25/$B$2 -> 0.48884281
A26: 9 | B26: =IF(A26<=$B$8,"上升期",IF(A26<=$B$9,"巔峰期",IF(A26<=$B$10,"停滯期","衰退期"))) -> 上升期 | C26: =IF(B26="上升期",$B$11,IF(B26="巔峰期",$B$12,IF(B26="停滯期",$B$13,$B$14))) -> 1.2 | D26: =$B$4*(($B$2-E25)/100)*C26*$B$5*$B$6*$B$7 -> 1.2617404 | E26: =MIN(E25+D26,$B$2) -> 42.813379 | F26: =E26/$B$2 -> 0.50368681
A27: 10 | B27: =IF(A27<=$B$8,"上升期",IF(A27<=$B$9,"巔峰期",IF(A27<=$B$10,"停滯期","衰退期"))) -> 上升期 | C27: =IF(B27="上升期",$B$11,IF(B27="巔峰期",$B$12,IF(B27="停滯期",$B$13,$B$14))) -> 1.2 | D27: =$B$4*(($B$2-E26)/100)*C27*$B$5*$B$6*$B$7 -> 1.2250995 | E27: =MIN(E26+D27,$B$2) -> 44.038479 | F27: =E27/$B$2 -> 0.51809975
A28: 11 | B28: =IF(A28<=$B$8,"上升期",IF(A28<=$B$9,"巔峰期",IF(A28<=$B$10,"停滯期","衰退期"))) -> 上升期 | C28: =IF(B28="上升期",$B$11,IF(B28="巔峰期",$B$12,IF(B28="停滯期",$B$13,$B$14))) -> 1.2 | D28: =$B$4*(($B$2-E27)/100)*C28*$B$5*$B$6*$B$7 -> 1.1895226 | E28: =MIN(E27+D28,$B$2) -> 45.228001 | F28: =E28/$B$2 -> 0.53209413
A29: 12 | B29: =IF(A29<=$B$8,"上升期",IF(A29<=$B$9,"巔峰期",IF(A29<=$B$10,"停滯期","衰退期"))) -> 上升期 | C29: =IF(B29="上升期",$B$11,IF(B29="巔峰期",$B$12,IF(B29="停滯期",$B$13,$B$14))) -> 1.2 | D29: =$B$4*(($B$2-E28)/100)*C29*$B$5*$B$6*$B$7 -> 1.1549788 | E29: =MIN(E28+D29,$B$2) -> 46.38298 | F29: =E29/$B$2 -> 0.54568212
A30: 13 | B30: =IF(A30<=$B$8,"上升期",IF(A30<=$B$9,"巔峰期",IF(A30<=$B$10,"停滯期","衰退期"))) -> 上升期 | C30: =IF(B30="上升期",$B$11,IF(B30="巔峰期",$B$12,IF(B30="停滯期",$B$13,$B$14))) -> 1.2 | D30: =$B$4*(($B$2-E29)/100)*C30*$B$5*$B$6*$B$7 -> 1.1214383 | E30: =MIN(E29+D30,$B$2) -> 47.504418 | F30: =E30/$B$2 -> 0.55887551
... A167: 150 | B167: =IF(A167<=$B$8,"上升期",IF(A167<=$B$9,"巔峰期",IF(A167<=$B$10,"停滯期","衰退期"))) -> 衰退期 | C167: =IF(B167="上升期",$B$11,IF(B167="巔峰期",$B$12,IF(B167="停滯期",$B$13,$B$14))) -> 0.1 | D167: =$B$4*(($B$2-E166)/100)*C167*$B$5*$B$6*$B$7 -> 0.0055969903 | E167: =MIN(E166+D167,$B$2) -> 82.692791 | F167: =E167/$B$2 -> 0.97285637
A169: 調整上方藍字輸入值，觀察第 5 欄「累積能力值」大約在第幾週追上潛力上限——藉此判斷一個賽季
A170: (約52週)的訓練量，能否讓馬匹在巔峰期前把潛力用完，或是巔峰期都還沒練滿、潛力被浪費掉。

Sheet 財務模擬
A1: 小馬房一年(52週)現金流試算 | D1: 公式來源: 經營/財務系統.md 的收入/支出項目分類，數值為測試用假設。
A2: 馬房馬匹數 | B2: 5
A3: 起始資金 | B3: 50000
A4: 每匹馬週固定支出(假設，含馬房/訓練/獸醫) | B4: 400
A5: 設施週維護費(假設，固定) | B5: 500
A6: 人力週固定費(假設，訓練師/獸醫底薪) | B6: 800
A7: 平均每匹馬週比賽收入期望值(假設) | B7: 350
A8: 週贊助/週邊收入(假設，固定) | B8: 200
A11: 週次 | B11: 收入 | C11: 支出 | D11: 淨現金流 | E11: 累積資金 | F11: 狀態
A12: 1 | B12: =$B$2*$B$7+$B$8 -> 1950 | C12: =$B$2*$B$4+$B$5+$B$6 -> 3300 | D12: =B12-C12 -> -1350 | E12: =$B$3+D12 -> 48650 | F12: =IF(E12<0,"負資產警示","")
A13: 2 | B13: =$B$2*$B$7+$B$8 -> 1950 | C13: =$B$2*$B$4+$B$5+$B$6 -> 3300 | D13: =B13-C13 -> -1350 | E13: =E12+D13 -> 47300 | F13: =IF(E13<0,"負資產警示","")
A14: 3 | B14: =$B$2*$B$7+$B$8 -> 1950 | C14: =$B$2*$B$4+$B$5+$B$6 -> 3300 | D14: =B14-C14 -> -1350 | E14: =E13+D14 -> 45950 | F14: =IF(E14<0,"負資產警示","")
A15: 4 | B15: =$B$2*$B$7+$B$8 -> 1950 | C15: =$B$2*$B$4+$B$5+$B$6 -> 3300 | D15: =B15-C15 -> -1350 | E15: =E14+D15 -> 44600 | F15: =IF(E15<0,"負資產警示","")
A16: 5 | B16: =$B$2*$B$7+$B$8 -> 1950 | C16: =$B$2*$B$4+$B$5+$B$6 -> 3300 | D16: =B16-C16 -> -1350 | E16: =E15+D16 -> 43250 | F16: =IF(E16<0,"負資產警示","")
A17: 6 | B17: =$B$2*$B$7+$B$8 -> 1950 | C17: =$B$2*$B$4+$B$5+$B$6 -> 3300 | D17: =B17-C17 -> -1350 | E17: =E16+D17 -> 41900 | F17: =IF(E17<0,"負資產警示","")
A18: 7 | B18: =$B$2*$B$7+$B$8 -> 1950 | C18: =$B$2*$B$4+$B$5+$B$6 -> 3300 | D18: =B18-C18 -> -1350 | E18: =E17+D18 -> 40550 | F18: =IF(E18<0,"負資產警示","")
A19: 8 | B19: =$B$2*$B$7+$B$8 -> 1950 | C19: =$B$2*$B$4+$B$5+$B$6 -> 3300 | D19: =B19-C19 -> -1350 | E19: =E18+D19 -> 39200 | F19: =IF(E19<0,"負資產警示","")
A20: 9 | B20: =$B$2*$B$7+$B$8 -> 1950 | C20: =$B$2*$B$4+$B$5+$B$6 -> 3300 | D20: =B20-C20 -> -1350 | E20: =E19+D20 -> 37850 | F20: =IF(E20<0,"負資產警示","")
A21: 10 | B21: =$B$2*$B$7+$B$8 -> 1950 | C21: =$B$2*$B$4+$B$5+$B$6 -> 3300 | D21: =B21-C21 -> -1350 | E21: =E20+D21 -> 36500 | F21: =IF(E21<0,"負資產警示","")
A22: 11 | B22: =$B$2*$B$7+$B$8 -> 1950 | C22: =$B$2*$B$4+$B$5+$B$6 -> 3300 | D22: =B22-C22 -> -1350 | E22: =E21+D22 -> 35150 | F22: =IF(E22<0,"負資產警示","")
A23: 12 | B23: =$B$2*$B$7+$B$8 -> 1950 | C23: =$B$2*$B$4+$B$5+$B$6 -> 3300 | D23: =B23-C23 -> -1350 | E23: =E22+D23 -> 33800 | F23: =IF(E23<0,"負資產警示","")
A24: 13 | B24: =$B$2*$B$7+$B$8 -> 1950 | C24: =$B$2*$B$4+$B$5+$B$6 -> 3300 | D24: =B24-C24 -> -1350 | E24: =E23+D24 -> 32450 | F24: =IF(E24<0,"負資產警示","")
... A63: 52 | B63: =$B$2*$B$7+$B$8 -> 1950 | C63: =$B$2*$B$4+$B$5+$B$6 -> 3300 | D63: =B63-C63 -> -1350 | E63: =E62+D63 -> -20200 | F63: =IF(E63<0,"負資產警示","") -> 負資產警示
A65: 調整上方藍字輸入值，觀察「累積資金」欄位全年是否維持正值——藉此判斷平均比賽收入與固定支出
A66: 之間的落差有多大，以及新手馬主在還沒有明星馬前，能撐過幾週入不敷出的狀態。

Sheet 財務系統進階
A1: 小馬房一年(52週)現金流試算 — 加入拍賣購馬、分級獎金期望值、人員分成 | D1: 公式來源: 經營/財務系統.md 收支分類 + 賽事與生涯系統.md 獎金/分成規則 + 市場/拍賣系統.md，數值為測試用假設。
A2: 馬房馬匹數 | B2: 5
A3: 起始資金 | B3: 150000
A4: 每匹馬週固定支出(訓練+馬房費，假設) | B4: 350
A5: 設施週維護費(假設) | B5: 500
A6: 人力週固定費(訓練師/獸醫底薪，假設) | B6: 900
A7: 每匹馬出賽週期(每N週出賽1次，假設) | B7: 4
A8: 每次出賽報名費(假設) | B8: 800
A9: 一般賽基準獎金(地方一般賽Top3，假設) | B9: 15000
A10: 難度(輸入「簡單」或「困難」) | B10: 困難
A11: 困難的平均進帳期望比例(假設，保留硬核手感) | B11: 0.12
A12: 簡單的平均進帳期望比例(假設，調高比賽收入) | B12: 0.3
A13: 使用中的平均進帳期望比例(依上方難度自動判斷，不要手動覆寫) | B13: =IF(B10="簡單",B12,B11) -> 0.12
A14: 比賽獎金人員分成比例(騎師+訓練師，假設) | B14: 0.15
A15: 拍賣購馬支出(第20週一次性，假設) | B15: 35000
A16: 繁殖種馬費收入(第35週一次性，假設) | B16: 6000
A19: 週次 | B19: 是否出賽週 | C19: 報名費支出 | D19: 比賽獎金收入(期望值，已扣分成) | E19: 拍賣/繁殖一次性收支 | F19: 固定支出 | G19: 淨現金流 | H19: 累積資金 | I19: 狀態
A20: 1 | B20: =IF(MOD(A20,$B$7)=0,1,0) -> 0 | C20: =B20*$B$2*$B$8 -> 0 | D20: =B20*$B$2*$B$9*$B$13*(1-$B$14) -> 0 | E20: =IF(A20=20,-$B$15,0)+IF(A20=35,$B$16,0) -> 0 | F20: =$B$2*$B$4+$B$5+$B$6 -> 3150 | G20: =D20-C20+E20-F20 -> -3150 | H20: =$B$3+G20 -> 146850 | I20: =IF(H20<0,"負資產警示","")
A21: 2 | B21: =IF(MOD(A21,$B$7)=0,1,0) -> 0 | C21: =B21*$B$2*$B$8 -> 0 | D21: =B21*$B$2*$B$9*$B$13*(1-$B$14) -> 0 | E21: =IF(A21=20,-$B$15,0)+IF(A21=35,$B$16,0) -> 0 | F21: =$B$2*$B$4+$B$5+$B$6 -> 3150 | G21: =D21-C21+E21-F21 -> -3150 | H21: =H20+G21 -> 143700 | I21: =IF(H21<0,"負資產警示","")
A22: 3 | B22: =IF(MOD(A22,$B$7)=0,1,0) -> 0 | C22: =B22*$B$2*$B$8 -> 0 | D22: =B22*$B$2*$B$9*$B$13*(1-$B$14) -> 0 | E22: =IF(A22=20,-$B$15,0)+IF(A22=35,$B$16,0) -> 0 | F22: =$B$2*$B$4+$B$5+$B$6 -> 3150 | G22: =D22-C22+E22-F22 -> -3150 | H22: =H21+G22 -> 140550 | I22: =IF(H22<0,"負資產警示","")
A23: 4 | B23: =IF(MOD(A23,$B$7)=0,1,0) -> 1 | C23: =B23*$B$2*$B$8 -> 4000 | D23: =B23*$B$2*$B$9*$B$13*(1-$B$14) -> 7650 | E23: =IF(A23=20,-$B$15,0)+IF(A23=35,$B$16,0) -> 0 | F23: =$B$2*$B$4+$B$5+$B$6 -> 3150 | G23: =D23-C23+E23-F23 -> 500 | H23: =H22+G23 -> 141050 | I23: =IF(H23<0,"負資產警示","")
A24: 5 | B24: =IF(MOD(A24,$B$7)=0,1,0) -> 0 | C24: =B24*$B$2*$B$8 -> 0 | D24: =B24*$B$2*$B$9*$B$13*(1-$B$14) -> 0 | E24: =IF(A24=20,-$B$15,0)+IF(A24=35,$B$16,0) -> 0 | F24: =$B$2*$B$4+$B$5+$B$6 -> 3150 | G24: =D24-C24+E24-F24 -> -3150 | H24: =H23+G24 -> 137900 | I24: =IF(H24<0,"負資產警示","")
A25: 6 | B25: =IF(MOD(A25,$B$7)=0,1,0) -> 0 | C25: =B25*$B$2*$B$8 -> 0 | D25: =B25*$B$2*$B$9*$B$13*(1-$B$14) -> 0 | E25: =IF(A25=20,-$B$15,0)+IF(A25=35,$B$16,0) -> 0 | F25: =$B$2*$B$4+$B$5+$B$6 -> 3150 | G25: =D25-C25+E25-F25 -> -3150 | H25: =H24+G25 -> 134750 | I25: =IF(H25<0,"負資產警示","")
A26: 7 | B26: =IF(MOD(A26,$B$7)=0,1,0) -> 0 | C26: =B26*$B$2*$B$8 -> 0 | D26: =B26*$B$2*$B$9*$B$13*(1-$B$14) -> 0 | E26: =IF(A26=20,-$B$15,0)+IF(A26=35,$B$16,0) -> 0 | F26: =$B$2*$B$4+$B$5+$B$6 -> 3150 | G26: =D26-C26+E26-F26 -> -3150 | H26: =H25+G26 -> 131600 | I26: =IF(H26<0,"負資產警示","")
A27: 8 | B27: =IF(MOD(A27,$B$7)=0,1,0) -> 1 | C27: =B27*$B$2*$B$8 -> 4000 | D27: =B27*$B$2*$B$9*$B$13*(1-$B$14) -> 7650 | E27: =IF(A27=20,-$B$15,0)+IF(A27=35,$B$16,0) -> 0 | F27: =$B$2*$B$4+$B$5+$B$6 -> 3150 | G27: =D27-C27+E27-F27 -> 500 | H27: =H26+G27 -> 132100 | I27: =IF(H27<0,"負資產警示","")
A28: 9 | B28: =IF(MOD(A28,$B$7)=0,1,0) -> 0 | C28: =B28*$B$2*$B$8 -> 0 | D28: =B28*$B$2*$B$9*$B$13*(1-$B$14) -> 0 | E28: =IF(A28=20,-$B$15,0)+IF(A28=35,$B$16,0) -> 0 | F28: =$B$2*$B$4+$B$5+$B$6 -> 3150 | G28: =D28-C28+E28-F28 -> -3150 | H28: =H27+G28 -> 128950 | I28: =IF(H28<0,"負資產警示","")
A29: 10 | B29: =IF(MOD(A29,$B$7)=0,1,0) -> 0 | C29: =B29*$B$2*$B$8 -> 0 | D29: =B29*$B$2*$B$9*$B$13*(1-$B$14) -> 0 | E29: =IF(A29=20,-$B$15,0)+IF(A29=35,$B$16,0) -> 0 | F29: =$B$2*$B$4+$B$5+$B$6 -> 3150 | G29: =D29-C29+E29-F29 -> -3150 | H29: =H28+G29 -> 125800 | I29: =IF(H29<0,"負資產警示","")
A30: 11 | B30: =IF(MOD(A30,$B$7)=0,1,0) -> 0 | C30: =B30*$B$2*$B$8 -> 0 | D30: =B30*$B$2*$B$9*$B$13*(1-$B$14) -> 0 | E30: =IF(A30=20,-$B$15,0)+IF(A30=35,$B$16,0) -> 0 | F30: =$B$2*$B$4+$B$5+$B$6 -> 3150 | G30: =D30-C30+E30-F30 -> -3150 | H30: =H29+G30 -> 122650 | I30: =IF(H30<0,"負資產警示","")
A31: 12 | B31: =IF(MOD(A31,$B$7)=0,1,0) -> 1 | C31: =B31*$B$2*$B$8 -> 4000 | D31: =B31*$B$2*$B$9*$B$13*(1-$B$14) -> 7650 | E31: =IF(A31=20,-$B$15,0)+IF(A31=35,$B$16,0) -> 0 | F31: =$B$2*$B$4+$B$5+$B$6 -> 3150 | G31: =D31-C31+E31-F31 -> 500 | H31: =H30+G31 -> 123150 | I31: =IF(H31<0,"負資產警示","")
A32: 13 | B32: =IF(MOD(A32,$B$7)=0,1,0) -> 0 | C32: =B32*$B$2*$B$8 -> 0 | D32: =B32*$B$2*$B$9*$B$13*(1-$B$14) -> 0 | E32: =IF(A32=20,-$B$15,0)+IF(A32=35,$B$16,0) -> 0 | F32: =$B$2*$B$4+$B$5+$B$6 -> 3150 | G32: =D32-C32+E32-F32 -> -3150 | H32: =H31+G32 -> 120000 | I32: =IF(H32<0,"負資產警示","")
... A71: 52 | B71: =IF(MOD(A71,$B$7)=0,1,0) -> 1 | C71: =B71*$B$2*$B$8 -> 4000 | D71: =B71*$B$2*$B$9*$B$13*(1-$B$14) -> 7650 | E71: =IF(A71=20,-$B$15,0)+IF(A71=35,$B$16,0) -> 0 | F71: =$B$2*$B$4+$B$5+$B$6 -> 3150 | G71: =D71-C71+E71-F71 -> 500 | H71: =H70+G71 -> 4650 | I71: =IF(H71<0,"負資產警示","")
A73: 把「難度」欄位改成「簡單」或「困難」，可以切換套用哪一組平均進帳期望比例(對應財務系統.md
A74: 「難度設定」章節)：困難版維持12%，新手容易在一年內把資金燒到接近破產；簡單版調高到30%，
A75: 資金應該能穩定小幅成長。可用這兩種設定對照「累積資金」欄位末段(第52週)的差異。
A76: 調整上方藍字輸入值，觀察拍賣購馬(第20週)、繁殖收入(第35週)這類一次性大額現金流動，疊加在
A77: 常態比賽收入/固定支出之上時，「累積資金」是否會被打到負值——藉此判斷玩家在規劃大額支出
A78: (例如標下一匹貴馬)前，需要先累積多少緩衝資金才安全。

Sheet 繁殖世代模擬
A1: 三代繁殖世代模擬 — 檢查屬性/潛力隨世代遞增是否失控膨脹或退化，並示範近親繁殖懲罰 | F1: 公式來源: 繁殖/遺傳系統.md「屬性遺傳」「潛力」「近親繁殖」規則，馬匹/潛力與評估.md「整體潛力」。
A3: 名稱 | B3: 世代 | C3: 父 | D3: 母 | E3: 近親? | F3: 速度 | G3: 耐力 | H3: 加速 | I3: 力量 | J3: 根性 | K3: 智力 | L3: 起跑 | M3: 彎道 | N3: 戰術 | O3: 精神 | P3: 健康 | Q3: 整體潛力 | R3: 備註
A4: 父馬 | B4: Gen0 | C4: - | D4: - | E4: 否 | G4: 78 | H4: 70 | I4: 75 | J4: 68 | K4: 72 | L4: 65 | M4: 70 | N4: 66 | O4: 60 | P4: 68 | Q4: 80 | R4: 始祖種馬
A5: 母馬 | B5: Gen0 | C5: - | D5: - | E5: 否 | G5: 72 | H5: 80 | I5: 68 | J5: 60 | K5: 78 | L5: 70 | M5: 65 | N5: 72 | O5: 62 | P5: 74 | Q5: 78 | R5: 始祖繁殖母馬
A6: 外部種馬 | B6: Gen1 | C6: - | D6: - | E6: 否 | G6: 75 | H6: 68 | I6: 82 | J6: 74 | K6: 66 | L6: 72 | M6: 78 | N6: 70 | O6: 68 | P6: 65 | Q6: 82 | R6: 另外購入，與父馬母馬無血緣關係
A7: 子代A | B7: Gen1 | C7: =A4 -> 父馬 | D7: =A5 -> 母馬 | E7: 否 | G7: =MIN(100,MAX(0,ROUND(AVERAGE(G4,G5)+(RAND()-0.5)*8,0))) -> 72 | H7: =MIN(100,MAX(0,ROUND(AVERAGE(H4,H5)+(RAND()-0.5)*8,0))) -> 73 | I7: =MIN(100,MAX(0,ROUND(AVERAGE(I4,I5)+(RAND()-0.5)*8,0))) -> 74 | J7: =MIN(100,MAX(0,ROUND(AVERAGE(J4,J5)+(RAND()-0.5)*8,0))) -> 62 | K7: =MIN(100,MAX(0,ROUND(AVERAGE(K4,K5)+(RAND()-0.5)*8,0))) -> 77 | L7: =MIN(100,MAX(0,ROUND(AVERAGE(L4,L5)+(RAND()-0.5)*8,0))) -> 65 | M7: =MIN(100,MAX(0,ROUND(AVERAGE(M4,M5)+(RAND()-0.5)*8,0))) -> 71 | N7: =MIN(100,MAX(0,ROUND(AVERAGE(N4,N5)+(RAND()-0.5)*8,0))) -> 72 | ... P7: =MIN(100,MAX(0,ROUND(AVERAGE(P4,P5)+(RAND()-0.5)*8,0))) -> 71 | Q7: =MIN(100,MAX(0,ROUND(AVERAGE(Q4,Q5)+RAND()*20-8-0,0))) -> 71 | R7: 父馬×母馬，非近親，潛力「存在突破父母的可能」故加了正偏態隨機項
A8: 子代B | B8: Gen1 | C8: =A4 -> 父馬 | D8: =A5 -> 母馬 | E8: 否 | G8: =MIN(100,MAX(0,ROUND(AVERAGE(G4,G5)+(RAND()-0.5)*8,0))) -> 73 | H8: =MIN(100,MAX(0,ROUND(AVERAGE(H4,H5)+(RAND()-0.5)*8,0))) -> 77 | I8: =MIN(100,MAX(0,ROUND(AVERAGE(I4,I5)+(RAND()-0.5)*8,0))) -> 70 | J8: =MIN(100,MAX(0,ROUND(AVERAGE(J4,J5)+(RAND()-0.5)*8,0))) -> 65 | K8: =MIN(100,MAX(0,ROUND(AVERAGE(K4,K5)+(RAND()-0.5)*8,0))) -> 74 | L8: =MIN(100,MAX(0,ROUND(AVERAGE(L4,L5)+(RAND()-0.5)*8,0))) -> 64 | M8: =MIN(100,MAX(0,ROUND(AVERAGE(M4,M5)+(RAND()-0.5)*8,0))) -> 69 | N8: =MIN(100,MAX(0,ROUND(AVERAGE(N4,N5)+(RAND()-0.5)*8,0))) -> 66 | ... P8: =MIN(100,MAX(0,ROUND(AVERAGE(P4,P5)+(RAND()-0.5)*8,0))) -> 68 | Q8: =MIN(100,MAX(0,ROUND(AVERAGE(Q4,Q5)+RAND()*20-8-0,0))) -> 82 | R8: 同一對父母的第二胎，示範同樣血緣配對下潛力仍有隨機差異
A9: 孫代-正常配種 | B9: Gen2 | C9: =A7 -> 子代A | D9: =A6 -> 外部種馬 | E9: 否 | G9: =MIN(100,MAX(0,ROUND(AVERAGE(G7,G6)+(RAND()-0.5)*8,0))) -> 76 | H9: =MIN(100,MAX(0,ROUND(AVERAGE(H7,H6)+(RAND()-0.5)*8,0))) -> 70 | I9: =MIN(100,MAX(0,ROUND(AVERAGE(I7,I6)+(RAND()-0.5)*8,0))) -> 77 | J9: =MIN(100,MAX(0,ROUND(AVERAGE(J7,J6)+(RAND()-0.5)*8,0))) -> 67 | K9: =MIN(100,MAX(0,ROUND(AVERAGE(K7,K6)+(RAND()-0.5)*8,0))) -> 71 | L9: =MIN(100,MAX(0,ROUND(AVERAGE(L7,L6)+(RAND()-0.5)*8,0))) -> 66 | M9: =MIN(100,MAX(0,ROUND(AVERAGE(M7,M6)+(RAND()-0.5)*8,0))) -> 76 | N9: =MIN(100,MAX(0,ROUND(AVERAGE(N7,N6)+(RAND()-0.5)*8,0))) -> 70 | ... P9: =MIN(100,MAX(0,ROUND(AVERAGE(P7,P6)+(RAND()-0.5)*8,0))) -> 65 | Q9: =MIN(100,MAX(0,ROUND(AVERAGE(Q7,Q6)+RAND()*20-8-0,0))) -> 84 | R9: 子代A×外部種馬(無血緣)，正常配種對照組
A10: 孫代-近親配種 | B10: Gen2 | C10: =A7 -> 子代A | D10: =A8 -> 子代B | E10: 是 | G10: =MIN(100,MAX(0,ROUND(AVERAGE(G7,G8)+(RAND()-0.5)*8,0))) -> 73 | H10: =MIN(100,MAX(0,ROUND(AVERAGE(H7,H8)+(RAND()-0.5)*8,0))) -> 77 | I10: =MIN(100,MAX(0,ROUND(AVERAGE(I7,I8)+(RAND()-0.5)*8,0))) -> 68 | J10: =MIN(100,MAX(0,ROUND(AVERAGE(J7,J8)+(RAND()-0.5)*8,0))) -> 65 | K10: =MIN(100,MAX(0,ROUND(AVERAGE(K7,K8)+(RAND()-0.5)*8,0))) -> 78 | L10: =MIN(100,MAX(0,ROUND(AVERAGE(L7,L8)+(RAND()-0.5)*8,0))) -> 64 | M10: =MIN(100,MAX(0,ROUND(AVERAGE(M7,M8)+(RAND()-0.5)*8,0))) -> 71 | N10: =MIN(100,MAX(0,ROUND(AVERAGE(N7,N8)+(RAND()-0.5)*8,0))) -> 65 | ... P10: =MIN(100,MAX(0,ROUND(AVERAGE(P7,P8)+(RAND()-0.5)*8,0))) -> 72 | Q10: =MIN(100,MAX(0,ROUND(AVERAGE(Q7,Q8)+RAND()*20-8-15,0))) -> 56 | R10: 子代A×子代B(同窩兄妹)，示範近親繁殖對潛力上限的懲罰(公式內-15)
A12: 各世代平均整體潛力 | B12: Gen0 | C12: =AVERAGE(Q4,Q5) -> 79
B13: Gen1 | C13: =AVERAGE(Q7,Q8) -> 76.5
B14: Gen2(正常配種) | C14: =Q9 -> 84
B15: Gen2(近親配種) | C15: =Q10 -> 56
A17: 此分頁使用 RAND()，每次重新計算(recalc)結果都會重新洗牌，用來觀察隨機範圍是否合理，
A18: 而不是要看單一次的精確數字。
A19: 重點觀察：(1) 各世代平均整體潛力是否隨世代持續上升(潛力膨脹、後期馬全部頂級)或明顯下降
A20: (退化)；理想狀態應該在始祖水準附近小幅波動。(2)「孫代-近親配種」列的整體潛力，應該要能
A21: 穩定低於「孫代-正常配種」列，藉此驗證近親繁殖懲罰有確實反映在數值上。
